odoo/addons/profiler/README.rst
odoo/addons/profiler/__init__.py
odoo/addons/profiler/__manifest__.py
odoo/addons/profiler/hooks.py
odoo/addons/profiler/i18n/profiler.pot
odoo/addons/profiler/models/__init__.py
odoo/addons/profiler/models/ir_http.py
odoo/addons/profiler/models/profiler_profile.py
odoo/addons/profiler/security/ir.model.access.csv
odoo/addons/profiler/static/description/icon.png
odoo/addons/profiler/static/src/js/tour.js
odoo/addons/profiler/tests/__init__.py
odoo/addons/profiler/tests/test_profiling.py
odoo/addons/profiler/tests/test_profiling_ui.py
odoo/addons/profiler/views/assets.xml
odoo/addons/profiler/views/profiler_profile_view.xml
odoo11_addon_profiler-11.0.2.0.0.dist-info/METADATA
odoo11_addon_profiler-11.0.2.0.0.dist-info/WHEEL
odoo11_addon_profiler-11.0.2.0.0.dist-info/top_level.txt
odoo11_addon_profiler-11.0.2.0.0.dist-info/RECORD
