Metadata-Version: 2.1
Name: odoo11-addon-profiler
Version: 11.0.2.0.0
Summary: profiler
Home-page: https://github.com/OCA/server-tools/tree/12.0/profiler
Author: Vauxoo, Sunflower IT, Odoo Community Association (OCA)
Author-email: support@odoo-community.org
License: AGPL-3
Platform: UNKNOWN
Classifier: Programming Language :: Python
Classifier: Framework :: Odoo
Classifier: License :: OSI Approved :: GNU Affero General Public License v3
Requires-Python: >=2.7, !=3.0.*, !=3.1.*, !=3.2.*, !=3.3.*, !=3.4.*
Requires-Dist: odoo (<11.1dev,>=11.0a)
